liotbchain/__init__.py
liotbchain/block.py
liotbchain/blockchain.py
liotbchain/config.py
liotbchain/utils.py
liotbchain/database/__init__.py
liotbchain/database/db.py
liotbchain-0.0.8.dist-info/LICENSE
liotbchain-0.0.8.dist-info/METADATA
liotbchain-0.0.8.dist-info/WHEEL
liotbchain-0.0.8.dist-info/top_level.txt
liotbchain-0.0.8.dist-info/RECORD
