Metadata-Version: 2.1
Name: liotbchain
Version: 0.0.8
Summary: Python Lightweight IOT Blockchain framework
Home-page: https://github.com/sharhan-alhassan/liotbchain
Author: Sharhan Alhassan
Author-email: sharhanalhassan@gmail.com
Keywords: blockchain python iot framework
Classifier: Programming Language :: Python :: 3
Classifier: License :: OSI Approved :: MIT License
Classifier: Operating System :: OS Independent
Requires-Python: >=3.6
License-File: LICENSE
Requires-Dist: iniconfig ==2.0.0
Requires-Dist: packaging ==24.0
Requires-Dist: pluggy ==1.5.0
Requires-Dist: psycopg2-binary ==2.9.9
Requires-Dist: pytest ==8.2.2
Requires-Dist: pytest-mock ==3.14.0
Requires-Dist: python-dotenv ==1.0.1
Requires-Dist: setuptools ==70.0.0
